galileo_sdk/__init__.py
galileo_sdk/compat.py
galileo_sdk/galileo_sdk.py
galileo_sdk/mock_response.py
galileo_sdk/business/__init__.py
galileo_sdk/business/objects/__init__.py
galileo_sdk/business/objects/cargobays.py
galileo_sdk/business/objects/event.py
galileo_sdk/business/objects/exceptions.py
galileo_sdk/business/objects/jobs.py
galileo_sdk/business/objects/lz.py
galileo_sdk/business/objects/missions.py
galileo_sdk/business/objects/profiles.py
galileo_sdk/business/objects/stations.py
galileo_sdk/business/objects/universes.py
galileo_sdk/business/services/__init__.py
galileo_sdk/business/services/cargobays.py
galileo_sdk/business/services/jobs.py
galileo_sdk/business/services/log.py
galileo_sdk/business/services/lz.py
galileo_sdk/business/services/missions.py
galileo_sdk/business/services/profiles.py
galileo_sdk/business/services/stations.py
galileo_sdk/business/services/universes.py
galileo_sdk/business/utils/__init__.py
galileo_sdk/business/utils/generate_query_str.py
galileo_sdk/config/__init__.py
galileo_sdk/config/settings/__init__.py
galileo_sdk/config/settings/development.py
galileo_sdk/config/settings/production.py
galileo_sdk/data/__init__.py
galileo_sdk/data/events/__init__.py
galileo_sdk/data/events/connector.py
galileo_sdk/data/providers/__init__.py
galileo_sdk/data/providers/auth.py
galileo_sdk/data/repositories/__init__.py
galileo_sdk/data/repositories/cargobays.py
galileo_sdk/data/repositories/jobs.py
galileo_sdk/data/repositories/lz.py
galileo_sdk/data/repositories/missions.py
galileo_sdk/data/repositories/profiles.py
galileo_sdk/data/repositories/requests.py
galileo_sdk/data/repositories/settings.py
galileo_sdk/data/repositories/stations.py
galileo_sdk/data/repositories/universes.py
galileo_sdk/galileo_cli/__init__.py
galileo_sdk/galileo_cli/cargobays.py
galileo_sdk/galileo_cli/cli.py
galileo_sdk/galileo_cli/jobs.py
galileo_sdk/galileo_cli/lzs.py
galileo_sdk/galileo_cli/missions.py
galileo_sdk/galileo_cli/profiles.py
galileo_sdk-1.0.1.dist-info/LICENSE.txt
galileo_sdk-1.0.1.dist-info/METADATA
galileo_sdk-1.0.1.dist-info/WHEEL
galileo_sdk-1.0.1.dist-info/entry_points.txt
galileo_sdk-1.0.1.dist-info/top_level.txt
galileo_sdk-1.0.1.dist-info/RECORD
