Metadata-Version: 2.1
Name: galileo-sdk
Version: 1.0.1
Summary: UNKNOWN
Home-page: https://hypernetlabs.io/galileo/
Author: Hypernet Labs
Author-email: galileo@hypernetlabs.io
License: MIT
Platform: UNKNOWN
Requires-Python: >=2.7
License-File: LICENSE.txt
Requires-Dist: requests (>=2.21.0)
Requires-Dist: python-socketio[client] (==4.3.1)
Requires-Dist: python-engineio (==3.9.0)
Requires-Dist: chardet
Requires-Dist: mock
Requires-Dist: pathlib
Requires-Dist: termcolor (==1.1.0)
Requires-Dist: colorama (==0.4.3)
Requires-Dist: pyfiglet
Requires-Dist: click (==7.1.2)
Requires-Dist: click-shell
Requires-Dist: pandas
Requires-Dist: halo
Requires-Dist: curses-menu
Provides-Extra: docs
Requires-Dist: sphinx (>=2.2.0) ; extra == 'docs'
Requires-Dist: sphinx-material ; extra == 'docs'
